pythontextstats/__init__.py
pythontextstats-0.1.3.dist-info/licenses/LICENSE
pythontextstats-0.1.3.dist-info/METADATA
pythontextstats-0.1.3.dist-info/WHEEL
pythontextstats-0.1.3.dist-info/top_level.txt
pythontextstats-0.1.3.dist-info/RECORD
