Metadata-Version: 2.4
Name: pythontextstats
Version: 0.1.3
Summary: A Python package for text analysis
Home-page: https://github.com/Vigneshselvaraj1811/textstats
Author: Vignesh Selvaraj
Author-email: vigneshaasiga2020@gmail.com
Classifier: Programming Language :: Python :: 3
Classifier: License :: OSI Approved :: MIT License
Classifier: Operating System :: OS Independent
Requires-Python: >=3.6
License-File: LICENSE
Dynamic: author
Dynamic: author-email
Dynamic: classifier
Dynamic: description
Dynamic: description-content-type
Dynamic: home-page
Dynamic: license-file
Dynamic: requires-python
Dynamic: summary
